sokolpackage/main.py
sokolpackage-0.1.0.dist-info/METADATA
sokolpackage-0.1.0.dist-info/WHEEL
sokolpackage-0.1.0.dist-info/top_level.txt
sokolpackage-0.1.0.dist-info/RECORD
